BiobankRead-2.2.1.dist-info/DESCRIPTION.rst
BiobankRead-2.2.1.dist-info/METADATA
BiobankRead-2.2.1.dist-info/RECORD
BiobankRead-2.2.1.dist-info/WHEEL
BiobankRead-2.2.1.dist-info/metadata.json
BiobankRead-2.2.1.dist-info/top_level.txt
BiobankRead2/BiobankRead2.py
BiobankRead2/__init__.py
BiobankRead2/data/ICD10_UKB.tsv
BiobankRead2/data/ICD9_codes.csv
