Metadata-Version: 2.0
Name: BiobankRead
Version: 2.2.1
Summary: UKBiobank Python pre-processing
Home-page: UNKNOWN
Author: Deborah Schneider-luftman
Author-email: ds711@imperial.ac.uk
License: UNKNOWN
Platform: UNKNOWN
Requires-Dist: bs4
Requires-Dist: numpy
Requires-Dist: pandas
Requires-Dist: urllib3
